swarm/__init__.py
swarm/types.py
swarm/util.py
swarm/_async/__init__.py
swarm/_async/core.py
swarm/_async/types.py
swarm/_sync/__init__.py
swarm/_sync/core.py
swarm/_sync/types.py
swarm/repl/__init__.py
swarm/repl/repl.py
flex_swarm-0.1.1.dist-info/LICENSE
flex_swarm-0.1.1.dist-info/METADATA
flex_swarm-0.1.1.dist-info/WHEEL
flex_swarm-0.1.1.dist-info/top_level.txt
flex_swarm-0.1.1.dist-info/zip-safe
flex_swarm-0.1.1.dist-info/RECORD
