Metadata-Version: 2.1
Name: flex-swarm
Version: 0.1.1
Summary: A lightweight, stateless multi-agent orchestration framework. Forked from OpenAI''s swarm
Author: Nick Yu<wiseyu@gmail.com>
License: MIT
Requires-Python: >=3.10
License-File: LICENSE
Requires-Dist: openai>=1.33.0
Requires-Dist: pydantic
Provides-Extra: dev
Requires-Dist: jinja; extra == "dev"
Requires-Dist: numpy; extra == "dev"
Requires-Dist: pytest; extra == "dev"
Requires-Dist: requests; extra == "dev"
Requires-Dist: tqdm; extra == "dev"
Requires-Dist: pre-commit; extra == "dev"
Requires-Dist: instructor; extra == "dev"
